yescarpenter/IS_RSA.py
yescarpenter/__init__.py
yescarpenter/df_average.py
yescarpenter/pca.py
yescarpenter/ttest.py
yescarpenter-0.2.9.dist-info/licenses/LICENSE
yescarpenter-0.2.9.dist-info/METADATA
yescarpenter-0.2.9.dist-info/WHEEL
yescarpenter-0.2.9.dist-info/top_level.txt
yescarpenter-0.2.9.dist-info/RECORD
