Metadata-Version: 2.4
Name: yescarpenter
Version: 0.2.9
Summary: A library providing frequently used functions in data analysis for YESlab members and other researchers
Home-page: https://github.com/shangchengzhao/yescarpenter.git
Author: Shangcheng Zhao
Author-email: shangchengzhao@gmail.com
Classifier: Programming Language :: Python :: 3
Classifier: License :: OSI Approved :: MIT License
Classifier: Operating System :: OS Independent
Requires-Python: >=3.6
License-File: LICENSE
Requires-Dist: pandas
Requires-Dist: numpy
Requires-Dist: scikit-learn
Requires-Dist: matplotlib
Requires-Dist: seaborn
Dynamic: author
Dynamic: author-email
Dynamic: classifier
Dynamic: description
Dynamic: description-content-type
Dynamic: home-page
Dynamic: license-file
Dynamic: requires-dist
Dynamic: requires-python
Dynamic: summary
